Workbook

Sheet Supuestos
A1: AutoWAR - Supuestos de costo (celdas AMARILLAS = editables)
A2: Region: us-east-1 | Moneda: USD | Precios de referencia publicos (oct-2026). Incluye componentes To-Be (WAF, Cognito, Lambda Authorizer, entitlements). Validar en la calculadora AWS para cotizacion formal.
A4: PRECIOS UNITARIOS AWS | B4: Valor | C4: Unidad | D4: Fuente / nota
A5: Lambda: precio por request | B5: 2e-07 | C5: USD/request | D5: US$0.20 por 1M requests
A6: Lambda: precio por GB-segundo (x86) | B6: 1.66667e-05 | C6: USD/GB-s | D6: x86 on-demand
A7: Step Functions: por transicion (Standard) | B7: 2.5e-05 | C7: USD/transicion | D7: US$0.025 por 1.000 transiciones
A8: API Gateway REST: por request | B8: 3.5e-06 | C8: USD/request | D8: US$3.50 por 1M requests
A9: DynamoDB on-demand: por escritura (WRU) | B9: 1.25e-06 | C9: USD/escritura | D9: US$1.25 por 1M WRU
A10: DynamoDB on-demand: por lectura (RRU) | B10: 2.5e-07 | C10: USD/lectura | D10: US$0.25 por 1M RRU
A11: S3: almacenamiento por GB-mes | B11: 0.023 | C11: USD/GB-mes | D11: S3 Standard
A12: CloudWatch: por GB de logs ingeridos | B12: 0.5 | C12: USD/GB | D12: ingestion de logs
A13: KMS: por clave-mes | B13: 1 | C13: USD/clave-mes | D13: clave gestionada
A14: Secrets Manager: por secreto-mes | B14: 0.4 | C14: USD/secreto-mes | D14: +US$0.05 por 10k llamadas (despreciable)
A15: Bedrock Sonnet: por token entrada | B15: 3e-06 | C15: USD/token | D15: US$3 por 1M tokens in
A16: Bedrock Sonnet: por token salida | B16: 1.5e-05 | C16: USD/token | D16: US$15 por 1M tokens out
... A22: Cognito: por MAU (sobre capa gratis) | B22: 0.015 | C22: USD/MAU | D22: Essentials ~US$0.015/MAU; 10k MAU gratis (fed. menor)
A24: PARAMETROS POR ANALISIS (1 cuenta, 6 pilares) | B24: Valor | C24: Unidad | D24: Nota
A25: Invocaciones Lambda por analisis | B25: 8 | C25: invocaciones | D25: 6 pilares + orquestador + authorizer
A26: Duracion promedio por Lambda | B26: 60 | C26: segundos | D26: editable segun cuenta
A27: Memoria Lambda | B27: 1 | C27: GB | D27: 1024 MB
A28: Transiciones Step Functions | B28: 40 | C28: transiciones | D28: fan-out + joins
A29: Requests API Gateway | B29: 5 | C29: requests | D29: validar + analizar + polling
A30: Escrituras DynamoDB | B30: 22 | C30: escrituras | D30: resultados + items por pilar + entitlements
A31: Lecturas DynamoDB | B31: 24 | C31: lecturas | D31: resultados + lectura de entitlements
A32: Logs generados | B32: 0.05 | C32: GB | D32: ~50 MB de logs por analisis
A33: Tokens entrada Bedrock | B33: 15000 | C33: tokens | D33: hallazgos + contexto
A34: Tokens salida Bedrock | B34: 4000 | C34: tokens | D34: resumen redactado
A36: ESCENARIO MENSUAL | B36: Valor
A37: Analisis por mes | B37: 200
A38: Modelo Bedrock (1=Sonnet, 2=Haiku) | B38: 2
A39: Secretos (clientes) almacenados | B39: 10
A40: Claves KMS | B40: 1
A41: Hosting CloudFront+S3 (fijo/mes) | B41: 5
A42: WAF: web ACLs | B42: 1
A43: WAF: reglas/grupos | B43: 3
A44: WAF: requests/mes (millones) | B44: 1
A45: Cognito: MAU facturables (sobre capa gratis) | B45: 0
A46: Entitlements: items DynamoDB (clientes activos) | B46: 10

Sheet Costo por analisis
A1: Costo variable por 1 analisis (1 cuenta, 6 pilares)
A3: Servicio | B3: Formula (de donde sale) | C3: Costo USD
A4: Lambda - requests | B4: invocaciones x precio/request | C4: =Supuestos!$B$25*Supuestos!$B$5
A5: Lambda - computo (GB-s) | B5: inv x duracion(s) x memoria(GB) x precio/GB-s | C5: =Supuestos!$B$25*Supuestos!$B$26*Supuestos!$B$27*Supuestos!$B$6
A6: Step Functions | B6: transiciones x precio/transicion | C6: =Supuestos!$B$28*Supuestos!$B$7
A7: API Gateway | B7: requests x precio/request | C7: =Supuestos!$B$29*Supuestos!$B$8
A8: DynamoDB - escrituras | B8: escrituras x precio/WRU | C8: =Supuestos!$B$30*Supuestos!$B$9
A9: DynamoDB - lecturas | B9: lecturas x precio/RRU | C9: =Supuestos!$B$31*Supuestos!$B$10
A10: CloudWatch - logs | B10: GB logs x precio/GB | C10: =Supuestos!$B$32*Supuestos!$B$12
A11: Bedrock (segun modelo elegido) | B11: IF Sonnet vs Haiku: tokens_in x precio_in + tokens_out x precio_out | C11: =IF(Supuestos!$B$38=1,Supuestos!$B$33*Supuestos!$B$15+Supuestos!$B$34*Supuestos!$B$16,Supuestos!$B$33*Supuestos!$B$17+Supuestos!$B$34*Supuestos!$B$18)
A12: WAF - requests (parte variable) | B12: (requests analisis / 1e6) x precio/millon [despreciable por analisis] | C12: =(Supuestos!$B$29/1000000)*Supuestos!$B$21
A13: TOTAL variable por analisis | B13: suma de los componentes de arriba | C13: =SUM(C4:C12)
A15: Nota: | B15: Cambia el modelo en Supuestos (1=Sonnet, 2=Haiku) y veras recalcular Bedrock y el total. WAF y Cognito son costos mayormente FIJOS/mes (ver hoja Costo mensual), no por analisis.

Sheet Comparativa Bedrock
A1: Bedrock por analisis: Sonnet vs Haiku
A3: Concepto | B3: Sonnet (USD) | C3: Haiku (USD) | D3: Formula
A4: Tokens entrada | B4: =Supuestos!$B$33*Supuestos!$B$15 | C4: =Supuestos!$B$33*Supuestos!$B$17 | D4: tokens_in x precio_in
A5: Tokens salida | B5: =Supuestos!$B$34*Supuestos!$B$16 | C5: =Supuestos!$B$34*Supuestos!$B$18 | D5: tokens_out x precio_out
A6: Total Bedrock / analisis | B6: =SUM(B4:B5) | C6: =SUM(C4:C5)

Sheet Costo mensual
A1: Costo mensual estimado (variable + fijo)
A3: Concepto | B3: Formula | C3: USD/mes
A4: Variable: analisis del mes | B4: analisis/mes x costo por analisis | C4: =Supuestos!$B$37*'Costo por analisis'!$C$13
A5: Fijo: Secrets Manager | B5: secretos x precio/secreto-mes | C5: =Supuestos!$B$39*Supuestos!$B$14
A6: Fijo: KMS | B6: claves x precio/clave-mes | C6: =Supuestos!$B$40*Supuestos!$B$13
A7: Fijo: Hosting CloudFront+S3 | B7: valor fijo editable en Supuestos | C7: =Supuestos!$B$41
A8: Fijo: WAF (web ACL + reglas) | B8: webACLs x precio_acl + reglas x precio_regla | C8: =Supuestos!$B$42*Supuestos!$B$19+Supuestos!$B$43*Supuestos!$B$20
A9: Variable: WAF requests | B9: millones_req x precio/millon | C9: =Supuestos!$B$44*Supuestos!$B$21
A10: Variable: Cognito MAU | B10: MAU facturables x precio/MAU | C10: =Supuestos!$B$45*Supuestos!$B$22
A11: TOTAL mensual estimado | B11: suma variable + fijos | C11: =SUM(C4:C10)
A13: Costo medio por analisis (incl. fijos) | B13: total mensual / analisis del mes | C13: =C11/Supuestos!$B$37

Sheet Sensibilidad
A1: Sensibilidad: costo mensual segun volumen de analisis
A3: Volumen base (editable): | C3: 50 | D3: <- cambia este 50 y toda la tabla se recalcula
A5: Factor | B5: Analisis/mes | C5: Variable (USD/mes) | D5: Fijos (USD/mes) | E5: Total (USD/mes) | F5: Costo medio/analisis
A6: 1 | B6: =$C$3*A6 | C6: =B6*'Costo por analisis'!$C$13 | D6: =(Supuestos!$B$39*Supuestos!$B$14+Supuestos!$B$40*Supuestos!$B$13+Supuestos!$B$41+Supuestos!$B$42*Supuestos!$B$19+Supuestos!$B$43*Supuestos!$B$20+Supuestos!$B$44*Supuestos!$B$21+Supuestos!$B$45*Supuestos!$B$22) | E6: =C6+D6 | F6: =IF(B6=0,0,E6/B6)
A7: 2 | B7: =$C$3*A7 | C7: =B7*'Costo por analisis'!$C$13 | D7: =(Supuestos!$B$39*Supuestos!$B$14+Supuestos!$B$40*Supuestos!$B$13+Supuestos!$B$41+Supuestos!$B$42*Supuestos!$B$19+Supuestos!$B$43*Supuestos!$B$20+Supuestos!$B$44*Supuestos!$B$21+Supuestos!$B$45*Supuestos!$B$22) | E7: =C7+D7 | F7: =IF(B7=0,0,E7/B7)
A8: 4 | B8: =$C$3*A8 | C8: =B8*'Costo por analisis'!$C$13 | D8: =(Supuestos!$B$39*Supuestos!$B$14+Supuestos!$B$40*Supuestos!$B$13+Supuestos!$B$41+Supuestos!$B$42*Supuestos!$B$19+Supuestos!$B$43*Supuestos!$B$20+Supuestos!$B$44*Supuestos!$B$21+Supuestos!$B$45*Supuestos!$B$22) | E8: =C8+D8 | F8: =IF(B8=0,0,E8/B8)
A9: 10 | B9: =$C$3*A9 | C9: =B9*'Costo por analisis'!$C$13 | D9: =(Supuestos!$B$39*Supuestos!$B$14+Supuestos!$B$40*Supuestos!$B$13+Supuestos!$B$41+Supuestos!$B$42*Supuestos!$B$19+Supuestos!$B$43*Supuestos!$B$20+Supuestos!$B$44*Supuestos!$B$21+Supuestos!$B$45*Supuestos!$B$22) | E9: =C9+D9 | F9: =IF(B9=0,0,E9/B9)
A10: 20 | B10: =$C$3*A10 | C10: =B10*'Costo por analisis'!$C$13 | D10: =(Supuestos!$B$39*Supuestos!$B$14+Supuestos!$B$40*Supuestos!$B$13+Supuestos!$B$41+Supuestos!$B$42*Supuestos!$B$19+Supuestos!$B$43*Supuestos!$B$20+Supuestos!$B$44*Supuestos!$B$21+Supuestos!$B$45*Supuestos!$B$22) | E10: =C10+D10 | F10: =IF(B10=0,0,E10/B10)
A12: Notas: | B12: La columna Factor multiplica el volumen base. Con base=50 veras 50, 100, 200, 500, 1000. El costo por analisis sale de 'Costo por analisis'. Los Fijos ahora incluyen WAF y Cognito del To-Be.

Sheet Verif. Calculadora AWS
A1: Verificacion vs AWS Pricing Calculator (200 analisis/mes, modelo Sonnet, us-east-1)
A2: URL de la estimacion en la calculadora de AWS (precios al 2026-10-16):
A3: https://calculator.aws/#/estimate?id=9522a31ec4a7ecf35ed6def968263ccf9fd3711f
A4: Version con precios computados (Update+Share):
A5: https://calculator.aws/#/estimate?id=0ea593458fbb3a44f0a11b361ff5b7e7261c5671
A6: Estimacion To-Be (incluye WAF + Cognito + Bedrock Sonnet, 200 analisis/mes, us-east-1):
A7: https://calculator.aws/#/estimate?id=8748b8884c260d78b625d6ce3fbf631f45f8e552
A8: Servicio | B8: Excel (USD/mes) | C8: Calculadora (USD/mes) | D8: Dif. | E8: Nota
A9: Lambda | B9: 1.4 | C9: 0 | D9: =C9-B9 | E9: Calc muestra 0 (redondeo de su vista); real ~1.40
A10: Step Functions | B10: 0.2 | C10: 0.1 | D10: =C10-B10 | E10: Calc aplica matiz de tier en transiciones
A11: API Gateway | B11: 0 | C11: 0 | D11: =C11-B11 | E11: Ambos ~0 a este volumen
A12: CloudWatch | B12: 5 | C12: 5.05 | D12: =C12-B12 | E12: Calc suma cargo fijo de almacenamiento de logs
A13: DynamoDB | B13: 0.01 | C13: n/d | D13: - | E13: Centavos; servicio sin campos expuestos en calc
A14: Bedrock (Sonnet) | B14: 21 | C14: 20.99 | D14: =C14-B14 | E14: COINCIDE (dif. por redondeo de tokens)
A15: Secrets Manager | B15: 4 | C15: 4.05 | D15: =C15-B15 | E15: Calc suma llamadas API
A16: KMS | B16: 1 | C16: 1.06 | D16: =C16-B16 | E16: Calc suma requests simetricas
A17: WAF (To-Be) | B17: 8.3 | C17: por verificar | D17: - | E17: web ACL 5 + 3 reglas 3 + 1M req 0.60
A18: Cognito (To-Be) | B18: 0 | C18: por verificar | D18: - | E18: MAU dentro de capa gratis Essentials en escenario base
A19: Hosting CloudFront+S3 | B19: 5 | C19: n/d | D19: - | E19: Fijo estimado
A20: TOTAL | B20: =SUM(B9:B19)
A22: Conclusion: | B22: El To-Be agrega WAF (~US$8/mes fijo) y Cognito (~0 en volumen bajo, crece con MAU). Los componentes dominantes del As-Is (Bedrock, CloudWatch, Secrets, KMS) ya estaban verificados contra la calculadora con diferencias de centavos. Pendiente: nueva estimacion en la calculadora incluyendo WAF+Cognito.

Sheet Ambientes
A1: Costos AWS por ambiente (Produccion vs Staging)
A2: Produccion = 200 analisis/mes (celda Supuestos B37). Staging = volumen editable abajo.
A4: PARAMETROS STAGING (editables) | B4: Valor
A5: Analisis por mes (staging) | B5: 50
A6: WAF: web ACLs (staging) | B6: 1
A7: WAF: reglas/grupos (staging) | B7: 1
A8: WAF: requests/mes millones (staging) | B8: 0.1
A9: Hosting CloudFront+S3 (staging) | B9: 5
A10: Secretos almacenados (staging) | B10: 3
A11: Claves KMS (staging) | B11: 1
A13: Concepto | B13: Produccion (USD/mes) | C13: Staging (USD/mes) | D13: Formula base
A14: Variable: analisis del mes | B14: =Supuestos!$B$37*'Costo por analisis'!$C$13 | C14: =$B$5*'Costo por analisis'!$C$13 | D14: analisis x costo/analisis
A15: Fijo: Secrets Manager | B15: =Supuestos!$B$39*Supuestos!$B$14 | C15: =$B$10*Supuestos!$B$14 | D15: secretos x precio
A16: Fijo: KMS | B16: =Supuestos!$B$40*Supuestos!$B$13 | C16: =$B$11*Supuestos!$B$13 | D16: claves x precio
A17: Fijo: Hosting CloudFront+S3 | B17: =Supuestos!$B$41 | C17: =$B$9 | D17: valor fijo
A18: Fijo: WAF (web ACL + reglas) | B18: =Supuestos!$B$42*Supuestos!$B$19+Supuestos!$B$43*Supuestos!$B$20 | C18: =$B$6*Supuestos!$B$19+$B$7*Supuestos!$B$20 | D18: ACLs x precio + reglas x precio
A19: Variable: WAF requests | B19: =Supuestos!$B$44*Supuestos!$B$21 | C19: =$B$8*Supuestos!$B$21 | D19: millones req x precio
A20: Variable: Cognito MAU | B20: =Supuestos!$B$45*Supuestos!$B$22 | C20: =0 | D20: MAU x precio (staging ~0)
A21: TOTAL AWS por ambiente | B21: =SUM(B14:B20) | C21: =SUM(C14:C20)
A23: CONSOLIDADO AWS (Prod + Staging)
A24: Total AWS mensual (ambos ambientes) | B24: =B21+C21
A25: Total AWS anual (ambos ambientes) | B25: =B24*12
A26: Equivalente COP/mes (TRM 3500) | B26: =B24*3500

Sheet Inversion y OPEX
A1: Inversion inicial y gastos operativos (OPEX)
A3: INVERSION INICIAL (una vez) | B3: Valor | C3: USD | D3: Nota
A4: Horas de desarrollo | B4: 360
A5: Horas otras areas | B5: 360
A6: Tarifa (USD/hora) | B6: 30
A7: Horas totales | C7: =B4+B5
A8: Costo total desarrollo (USD) | C8: =(B4+B5)*B6
A9: Equivalente COP (TRM 3500) | C9: =C8*3500
A11: OPEX RECURRENTE | B11: USD/mes | C11: USD/anio | D11: Nota
A12: AWS (Prod + Staging) | B12: =Ambientes!$B$24 | C12: =B12*12 | D12: consolidado hoja Ambientes
A13: Kiro (plan Power) | B13: 200 | C13: =B13*12 | D13: USD$200/mes, 10k creditos (uso ~1.500/mes)
A14: OPEX TOTAL | B14: =B12+B13 | C14: =C12+C13
A15: OPEX TOTAL COP/mes (TRM 3500) | B15: =B14*3500
A17: Nota | B17: Kiro Power incluye 10.000 creditos; el uso previsto (~1.500/mes) cabe en planes menores. Se usa Power por indicacion del equipo.

Sheet Resumen Financiero
A1: Resumen financiero (3 escenarios, horizonte 3 anios)
A2: Moneda USD | TRM COP 3500 | Tasa de descuento (editable): | E2: 0.14
A4: SUPUESTOS DE INGRESO (editables) | B4: Conservador | C4: Base | D4: Optimista
A5: ARPU (USD/cuenta/mes) | B5: 95 | C5: 125 | D5: 160
A6: Cuentas activas Ano 1 | B6: 6 | C6: 10 | D6: 18
A7: Cuentas activas Ano 2 | B7: 14 | C7: 26 | D7: 48
A8: Cuentas activas Ano 3 | B8: 26 | C8: 55 | D8: 100
A10: Ingresos Ano 1 (USD) | B10: =B6*B5*12 | C10: =C6*C5*12 | D10: =D6*D5*12
A11: Ingresos Ano 2 (USD) | B11: =B7*B5*12 | C11: =C7*C5*12 | D11: =D7*D5*12
A12: Ingresos Ano 3 (USD) | B12: =B8*B5*12 | C12: =C8*C5*12 | D12: =D8*D5*12
A13: OPEX Ano 1 (USD) | B13: ='Inversion y OPEX'!$C$14 | C13: ='Inversion y OPEX'!$C$14 | D13: ='Inversion y OPEX'!$C$14
A14: OPEX Ano 2 (USD) | B14: ='Inversion y OPEX'!$C$14*1.12 | C14: ='Inversion y OPEX'!$C$14*1.12 | D14: ='Inversion y OPEX'!$C$14*1.12
A15: OPEX Ano 3 (USD) | B15: ='Inversion y OPEX'!$C$14*1.25 | C15: ='Inversion y OPEX'!$C$14*1.25 | D15: ='Inversion y OPEX'!$C$14*1.25
A16: EBITDA Ano 1 (USD) | B16: =B10-B13 | C16: =C10-C13 | D16: =D10-D13
A17: EBITDA Ano 2 (USD) | B17: =B11-B14 | C17: =C11-C14 | D17: =D11-D14
A18: EBITDA Ano 3 (USD) | B18: =B12-B15 | C18: =C12-C15 | D18: =D12-D15
A19: Inversion inicial (USD) | B19: ='Inversion y OPEX'!$C$8 | C19: ='Inversion y OPEX'!$C$8 | D19: ='Inversion y OPEX'!$C$8
A21: INDICADORES | B21: Conservador | C21: Base | D21: Optimista
A22: EBITDA acumulado 3 anios | B22: =SUM(B16:B18) | C22: =SUM(C16:C18) | D22: =SUM(D16:D18)
A23: ROI 3 anios (%) | B23: =(B22-B19)/B19 | C23: =(C22-C19)/C19 | D23: =(D22-D19)/D19
A24: VPN (USD) | B24: =-B19 + B16/(1+$E$2) + B17/(1+$E$2)^2 + B18/(1+$E$2)^3 | C24: =-C19 + C16/(1+$E$2) + C17/(1+$E$2)^2 + C18/(1+$E$2)^3 | D24: =-D19 + D16/(1+$E$2) + D17/(1+$E$2)^2 + D18/(1+$E$2)^3
A25: TIR (%) | B25: =IRR(B28:B31) | C25: =IRR(C28:C31) | D25: =IRR(D28:D31)
A26: Payback simple (meses, base EBITDA Ano 1) | B26: =B19/(B16/12) | C26: =C19/(C16/12) | D26: =D19/(D16/12)
A28: Flujo 0 (=-inversion) | B28: =-B19 | C28: =-C19 | D28: =-D19
A29: Flujo Ano 1 | B29: =B16 | C29: =C16 | D29: =D16
A30: Flujo Ano 2 | B30: =B17 | C30: =C17 | D30: =D17
A31: Flujo Ano 3 | B31: =B18 | C31: =C18 | D31: =D18
A33: Nota: ROI = (EBITDA acumulado - inversion)/inversion. VPN descuenta los EBITDA anuales a la tasa editable (E2). TIR via IRR sobre flujos anuales (filas 28-31). El Payback simple usa el EBITDA mensual del Ano 1 (metodo conservador/lineal); el payback real considerando el crecimiento de los Anos 2-3 es menor (ver documento de analisis). Cambia ARPU, cuentas o la tasa y todo recalcula.
